ipython_async/__init__.py
ipython_async/magics.py
tests/__init__.py
tests/conftest.py
tests/test_magics.py
ipython_async-0.1.0.dist-info/LICENSE
ipython_async-0.1.0.dist-info/METADATA
ipython_async-0.1.0.dist-info/WHEEL
ipython_async-0.1.0.dist-info/top_level.txt
ipython_async-0.1.0.dist-info/RECORD
