Metadata-Version: 2.2
Name: ipython-async
Version: 0.1.0
Summary: Run cells asynchronously in IPython/Jupyter across multiple shells
Home-page: https://github.com/yourusername/ipython-async
Author: Amadou Wolfgang Cisse
Author-email: amadou.6e@googlemail.com
Classifier: Programming Language :: Python :: 3
Classifier: License :: OSI Approved :: MIT License
Classifier: Operating System :: OS Independent
Classifier: Framework :: IPython
Classifier: Framework :: Jupyter
Requires-Python: >=3.6
License-File: LICENSE
Requires-Dist: ipython>=7.0.0
Requires-Dist: ipywidgets>=7.0.0
Dynamic: author
Dynamic: author-email
Dynamic: classifier
Dynamic: description
Dynamic: description-content-type
Dynamic: home-page
Dynamic: requires-dist
Dynamic: requires-python
Dynamic: summary
